{
	"configurations" : 
	[
		{
			"directories" : 
			[
				{
					"build" : ".",
					"hasInstallRule" : true,
					"jsonFile" : "directory-.-Debug-c133df3a1ccc919e6dc6.json",
					"minimumCMakeVersion" : 
					{
						"string" : "3.5"
					},
					"projectIndex" : 0,
					"source" : ".",
					"targetIndexes" : 
					[
						0,
						1,
						2,
						3,
						4,
						5,
						6,
						7,
						8
					]
				}
			],
			"name" : "Debug",
			"projects" : 
			[
				{
					"directoryIndexes" : 
					[
						0
					],
					"name" : "image_proc",
					"targetIndexes" : 
					[
						0,
						1,
						2,
						3,
						4,
						5,
						6,
						7,
						8
					]
				}
			],
			"targets" : 
			[
				{
					"directoryIndex" : 0,
					"id" : "crop_decimate::@6890427a1f51a3e7e1df",
					"jsonFile" : "target-crop_decimate-Debug-ff6f7e7152ef9e80b4c7.json",
					"name" : "crop_decimate",
					"projectIndex" : 0
				},
				{
					"directoryIndex" : 0,
					"id" : "crop_non_zero::@6890427a1f51a3e7e1df",
					"jsonFile" : "target-crop_non_zero-Debug-f54364aab15e0b34cbf6.json",
					"name" : "crop_non_zero",
					"projectIndex" : 0
				},
				{
					"directoryIndex" : 0,
					"id" : "debayer::@6890427a1f51a3e7e1df",
					"jsonFile" : "target-debayer-Debug-4d26f287bdfeaa43c0ac.json",
					"name" : "debayer",
					"projectIndex" : 0
				},
				{
					"directoryIndex" : 0,
					"id" : "image_proc::@6890427a1f51a3e7e1df",
					"jsonFile" : "target-image_proc-Debug-0db913fb9f1cd6de94e5.json",
					"name" : "image_proc",
					"projectIndex" : 0
				},
				{
					"directoryIndex" : 0,
					"id" : "image_proc_exe::@6890427a1f51a3e7e1df",
					"jsonFile" : "target-image_proc_exe-Debug-47b5d97f1580f08af2da.json",
					"name" : "image_proc_exe",
					"projectIndex" : 0
				},
				{
					"directoryIndex" : 0,
					"id" : "image_proc_uninstall::@6890427a1f51a3e7e1df",
					"jsonFile" : "target-image_proc_uninstall-Debug-25c5267e17efba074e3a.json",
					"name" : "image_proc_uninstall",
					"projectIndex" : 0
				},
				{
					"directoryIndex" : 0,
					"id" : "rectify::@6890427a1f51a3e7e1df",
					"jsonFile" : "target-rectify-Debug-87ee6793b5dc53eb0ea9.json",
					"name" : "rectify",
					"projectIndex" : 0
				},
				{
					"directoryIndex" : 0,
					"id" : "resize::@6890427a1f51a3e7e1df",
					"jsonFile" : "target-resize-Debug-e708107e3602362cb8e9.json",
					"name" : "resize",
					"projectIndex" : 0
				},
				{
					"directoryIndex" : 0,
					"id" : "uninstall::@6890427a1f51a3e7e1df",
					"jsonFile" : "target-uninstall-Debug-94ce038c3600392b87a5.json",
					"name" : "uninstall",
					"projectIndex" : 0
				}
			]
		}
	],
	"kind" : "codemodel",
	"paths" : 
	{
		"build" : "/home/corelab/ros2_stereo/src/image_proc/build",
		"source" : "/home/corelab/ros2_stereo/src/image_proc"
	},
	"version" : 
	{
		"major" : 2,
		"minor" : 4
	}
}
